LICENSE
MANIFEST.in
README.rst
setup.py
LBForum.egg-info/PKG-INFO
LBForum.egg-info/SOURCES.txt
LBForum.egg-info/dependency_links.txt
LBForum.egg-info/not-zip-safe
LBForum.egg-info/requires.txt
LBForum.egg-info/top_level.txt
lbforum/__init__.py
lbforum/admin.py
lbforum/api.py
lbforum/forms.py
lbforum/models.py
lbforum/profileviews.py
lbforum/serializers.py
lbforum/tests.py
lbforum/urls.py
lbforum/views.py
lbforum/fixtures/test_lbforum.json
lbforum/locale/ca/LC_MESSAGES/django.mo
lbforum/locale/ca/LC_MESSAGES/django.po
lbforum/locale/cs/LC_MESSAGES/django.mo
lbforum/locale/cs/LC_MESSAGES/django.po
lbforum/locale/zh-Hans/LC_MESSAGES/django.mo
lbforum/locale/zh-Hans/LC_MESSAGES/django.po
lbforum/management/__init__.py
lbforum/management/commands/__init__.py
lbforum/management/commands/init_lbforum_profile.py
lbforum/migrations/0001_initial.py
lbforum/migrations/0002_auto_20160811_0211.py
lbforum/migrations/__init__.py
lbforum/static/.DS_Store
lbforum/static/lbforum/.DS_Store
lbforum/static/lbforum/imgs/.DS_Store
lbforum/static/lbforum/imgs/accept.png
lbforum/static/lbforum/imgs/ajax-loader.gif
lbforum/static/lbforum/imgs/arrow_up.png
lbforum/static/lbforum/imgs/avatar.png
lbforum/static/lbforum/imgs/birthday.jpg
lbforum/static/lbforum/imgs/cake.png
lbforum/static/lbforum/imgs/cancel.png
lbforum/static/lbforum/imgs/delete.png
lbforum/static/lbforum/imgs/note_edit.png
lbforum/static/lbforum/scripts/.DS_Store
lbforum/static/lbforum/scripts/common.js
lbforum/static/lbforum/scripts/simple_tpl.js
lbforum/static/lbforum/scripts/upload_attachment.js
lbforum/static/lbforum/scripts/markitup/sets/bbcode/readme.txt
lbforum/static/lbforum/scripts/markitup/sets/bbcode/set.js
lbforum/static/lbforum/scripts/markitup/sets/bbcode/style.css
lbforum/static/lbforum/scripts/markitup/sets/bbcode/images/bold.png
lbforum/static/lbforum/scripts/markitup/sets/bbcode/images/clean.png
lbforum/static/lbforum/scripts/markitup/sets/bbcode/images/code.png
lbforum/static/lbforum/scripts/markitup/sets/bbcode/images/colors.png
lbforum/static/lbforum/scripts/markitup/sets/bbcode/images/fonts.png
lbforum/static/lbforum/scripts/markitup/sets/bbcode/images/hide.gif
